{
  "generator-jhipster": {
    "applicationIndex": 0,
    "applicationType": "gateway",
    "authenticationType": "oauth2",
    "baseName": "edsGateway",
    "blueprints": [],
    "buildTool": "maven",
    "cacheProvider": "no",
    "clientFramework": "react",
    "clientPackageManager": "npm",
    "clientTheme": "none",
    "clientThemeVariant": "",
    "creationTimestamp": 1670327374482,
    "databaseType": "mongodb",
    "devDatabaseType": "mongodb",
    "devServerPort": 9060,
    "dtoSuffix": "DTO",
    "enableGradleEnterprise": false,
    "enableHibernateCache": false,
    "enableSwaggerCodegen": false,
    "enableTranslation": true,
    "entities": ["EDSApplication"],
    "entitySuffix": "",
    "gradleEnterpriseHost": "",
    "jhiPrefix": "jhi",
    "jhipsterVersion": "7.9.3",
    "jwtSecretKey": "MzlmMDdhYjY5YWUxM2FiYjlmYmYyOTFiNmM2ZjBhY2JlYmQxOGJkOWIyMDdhNmU1NGEyNzliMzY0OWFlYTNlOGM3MmExNTMwNzFmZWVlYTI5YWFiYjI4YTIzZGFlMzU4NGY0ZTE5YmNkOGJhOWI3MzI1YzEwMDIwNzZhYTI5ZGQ=",
    "languages": ["en"],
    "lastLiquibaseTimestamp": 1670327434000,
    "messageBroker": false,
    "nativeLanguage": "en",
    "otherModules": [],
    "packageFolder": "fr/chu/bordeaux/eds",
    "packageName": "fr.chu.bordeaux.eds",
    "pages": [],
    "prodDatabaseType": "mongodb",
    "reactive": true,
    "searchEngine": false,
    "serverPort": "8080",
    "serviceDiscoveryType": "eureka",
    "skipCheckLengthOfIdentifier": false,
    "skipClient": false,
    "skipFakeData": false,
    "skipUserManagement": true,
    "testFrameworks": [],
    "websocket": false,
    "withAdminUi": true
  }
}
