{
  "generator-jhipster": {
    "authenticationType": "jwt",
    "cacheProvider": "ehcache",
    "serverPort": "8081",
    "serviceDiscoveryType": "eureka",
    "skipUserManagement": true,
    "baseName": "myApp1",
    "buildTool": "maven",
    "databaseType": "sql",
    "devDatabaseType": "h2Disk",
    "enableHibernateCache": true,
    "enableSwaggerCodegen": false,
    "enableTranslation": true,
    "jhiPrefix": "jhi",
    "languages": ["en"],
    "messageBroker": false,
    "prodDatabaseType": "mysql",
    "searchEngine": false,
    "skipClient": true,
    "testFrameworks": [],
    "websocket": false,
    "applicationType": "microservice",
    "packageName": "com.myapp",
    "packageFolder": "com/myapp",
    "jhipsterVersion": "7.1.0",
    "clientPackageManager": "npm",
    "dtoSuffix": "DTO",
    "entitySuffix": "",
    "reactive": false,
    "applicationIndex": 1,
    "skipServer": false,
    "skipCheckLengthOfIdentifier": false,
    "skipFakeData": false,
    "blueprints": [],
    "otherModules": [],
    "pages": [],
    "clientFramework": "angularX",
    "clientTheme": "none",
    "clientThemeVariant": "",
    "withAdminUi": false,
    "nativeLanguage": "en",
    "creationTimestamp": 1628499696215,
    "jwtSecretKey": "OTYxMzNmMzBkYzRiZmU0YjYyOThkMDA5MmI3MWRiODI3YmFlNjYzNWEwOGQyZmY3NWJkZDUzMTFiNGQ4ZjcyZDRkOTdiZGU5ZjYwMWJiZTlhZjJhMjM3ZjIwZGNiYjE4M2IxN2U4Njk2ODhjYjgwNWU5YjJkYWJjMjA1NmVjMTM=",
    "entities": ["A", "B"],
    "lastLiquibaseTimestamp": 1628499816000
  }
}
